python2jsonschema/__init__.py
python2jsonschema/cli.py
python2jsonschema/schematype.py
python2jsonschema-0.8.dist-info/LICENSE
python2jsonschema-0.8.dist-info/WHEEL
python2jsonschema-0.8.dist-info/METADATA
python2jsonschema-0.8.dist-info/entry_points.txt
python2jsonschema-0.8.dist-info/RECORD
